pyJJ/__init__.py
pyJJ/sql.py
pyJJ_chen/__init__.py
pyJJ_chen/sql.py
pyrdt/__init__.py
pyrdt/atom.py
pyrdt/combo.py
pyrdt/math.py
pyrdt/stat.py
pywfz/__init__.py
pywfz/sql.py
pyJJ_chen-1.0.0.dist-info/LICENSE
pyJJ_chen-1.0.0.dist-info/METADATA
pyJJ_chen-1.0.0.dist-info/WHEEL
pyJJ_chen-1.0.0.dist-info/top_level.txt
pyJJ_chen-1.0.0.dist-info/RECORD
