Metadata-Version: 2.1
Name: pyJJ-chen
Version: 1.0.0
Summary: reshape data type in py language 
Home-page: http://www.reshapedata.com
Author: JJLin
Author-email: JJLin@163.com
License: Apache License
Keywords: reshapedata,rdt,pyrdt
Platform: UNKNOWN
Requires-Python: >=3.6
License-File: LICENSE
Requires-Dist: requests
